pydantic_conf/__init__.py
pydantic_conf/config.py
pydantic_conf/py.typed
pydantic_conf/registry.py
pydantic_conf/secret.py
pydantic_conf-1.0.2.dist-info/METADATA
pydantic_conf-1.0.2.dist-info/WHEEL
pydantic_conf-1.0.2.dist-info/licenses/LICENSE
pydantic_conf-1.0.2.dist-info/RECORD
