Metadata-Version: 2.2
Name: pydantic-conf
Version: 1.0.1
Summary: Pydantic based application configuration
Author-email: "Yury Sokov (Yurzs)" <me@yurzs.dev>
License: Copyright 2024 Yury Sokov and other contributors
Classifier: Development Status :: 4 - Beta
License-File: LICENSE
